CHANGELOG
EXAMPLE-BOX.py
EXAMPLE-BoWTheme.py
EXAMPLE-Colourful.py
EXAMPLE-ManagedApp.py
EXAMPLE-Menus.py
EXAMPLE-MultilineEditable.py
EXAMPLE-OptionList.py
EXAMPLE-ThemeTransparent.py
EXAMPLE-WIDGETLIST.py
EXAMPLE-address-book.py
EXAMPLE-annotation.py
EXAMPLE-basic-editor.py
EXAMPLE-fuller.py
EXAMPLE-multipage_experimental.py
EXAMPLE-multiple-screens.py
EXAMPLE-mutt-like-annotated.py
EXAMPLE-mutt-like.py
EXAMPLE-muttactive.py
EXAMPLE-muttactivetraditional.py
EXAMPLE-nocolor.py
EXAMPLE-unicode-py3.py
EXAMPLE-unicode.py
EXAMPLE-waiting.py
EXAMPLE.py
LICENCE
MANIFEST.in
README.md
setup.py
docs/Makefile
docs/make.bat
npyscreen/__init__.py
npyscreen/apNPSApplication.py
npyscreen/apNPSApplicationAdvanced.py
npyscreen/apNPSApplicationEvents.py
npyscreen/apNPSApplicationManaged.py
npyscreen/apOptions.py
npyscreen/eveventhandler.py
npyscreen/fmActionForm.py
npyscreen/fmActionFormV2.py
npyscreen/fmFileSelector.py
npyscreen/fmForm.py
npyscreen/fmFormMultiPage.py
npyscreen/fmFormMutt.py
npyscreen/fmFormMuttActive.py
npyscreen/fmFormWithMenus.py
npyscreen/fmPopup.py
npyscreen/fm_form_edit_loop.py
npyscreen/globals.py
npyscreen/muMenu.py
npyscreen/muNewMenu.py
npyscreen/npysGlobalOptions.py
npyscreen/npysNPSFilteredData.py
npyscreen/npysThemeManagers.py
npyscreen/npysThemes.py
npyscreen/npysTree.py
npyscreen/npyspmfuncs.py
npyscreen/npyssafewrapper.py
npyscreen/proto_fm_screen_area.py
npyscreen/stdfmemail.py
npyscreen/utilNotify.py
npyscreen/util_viewhelp.py
npyscreen/wgFormControlCheckbox.py
npyscreen/wgNMenuDisplay.py
npyscreen/wgannotatetextbox.py
npyscreen/wgautocomplete.py
npyscreen/wgboxwidget.py
npyscreen/wgbutton.py
npyscreen/wgcheckbox.py
npyscreen/wgcombobox.py
npyscreen/wgdatecombo.py
npyscreen/wgeditmultiline.py
npyscreen/wgfilenamecombo.py
npyscreen/wggrid.py
npyscreen/wggridcoltitles.py
npyscreen/wgmonthbox.py
npyscreen/wgmultiline.py
npyscreen/wgmultilineeditable.py
npyscreen/wgmultilinetree.py
npyscreen/wgmultilinetreeselectable.py
npyscreen/wgmultiselect.py
pq_npyscreen.egg-info/PKG-INFO
pq_npyscreen.egg-info/SOURCES.txt
pq_npyscreen.egg-info/dependency_links.txt
pq_npyscreen.egg-info/top_level.txt