Metadata-Version: 1.1
Name: pq-npyscreen
Version: 4.9.1
Summary: Fork of npyscreen with community patches on top.
Home-page: http://www.npcole.com/npyscreen/
Author: Tomas Babej. Original code by Nicholas Cole
Author-email: tomas@proteinqure.com
License: New BSD License
Platform: UNKNOWN
Classifier: Development Status :: 5 - Production/Stable
Classifier: Programming Language :: Python :: 3
Classifier: Programming Language :: Python :: 2.6
Classifier: Programming Language :: Python :: 2.7
Classifier: Environment :: Console
Classifier: Operating System :: POSIX
Classifier: Environment :: Console :: Curses
Classifier: Intended Audience :: Developers
Classifier: License :: OSI Approved :: BSD License
Classifier: Topic :: Terminals
